my/arbtt.py
my/bluemaestro.py
my/cfg.py
my/codeforces.py
my/common.py
my/config.py
my/demo.py
my/endomondo.py
my/error.py
my/foursquare.py
my/goodreads.py
my/hypothesis.py
my/instapaper.py
my/kobo.py
my/lastfm.py
my/materialistic.py
my/orgmode.py
my/pdfs.py
my/pinboard.py
my/pocket.py
my/polar.py
my/py.typed
my/rescuetime.py
my/roamresearch.py
my/rtm.py
my/runnerup.py
my/simple.py
my/smscalls.py
my/taplog.py
my/topcoder.py
my/zotero.py
my/body/blood.py
my/body/weight.py
my/body/exercise/all.py
my/body/exercise/cardio.py
my/body/exercise/cross_trainer.py
my/body/sleep/common.py
my/body/sleep/main.py
my/books/kobo.py
my/browser/active_browser.py
my/browser/all.py
my/browser/common.py
my/browser/export.py
my/bumble/android.py
my/calendar/holidays.py
my/coding/commits.py
my/coding/github.py
my/core/__init__.py
my/core/__main__.py
my/core/_cpu_pool.py
my/core/cachew.py
my/core/cfg.py
my/core/common.py
my/core/compat.py
my/core/core_config.py
my/core/dataset.py
my/core/denylist.py
my/core/discovery_pure.py
my/core/error.py
my/core/experimental.py
my/core/freezer.py
my/core/hpi_compat.py
my/core/influxdb.py
my/core/init.py
my/core/internal.py
my/core/json.py
my/core/kompress.py
my/core/konsume.py
my/core/logging.py
my/core/mime.py
my/core/orgmode.py
my/core/pandas.py
my/core/preinit.py
my/core/pytest.py
my/core/query.py
my/core/query_range.py
my/core/serialize.py
my/core/source.py
my/core/sqlite.py
my/core/stats.py
my/core/structure.py
my/core/time.py
my/core/types.py
my/core/util.py
my/core/warnings.py
my/core/_deprecated/dataset.py
my/core/tests/auto_stats.py
my/core/tests/common.py
my/core/tests/denylist.py
my/core/tests/sqlite.py
my/core/tests/structure.py
my/core/tests/test_cachew.py
my/core/tests/test_cli.py
my/core/tests/test_config.py
my/core/tests/test_get_files.py
my/core/tests/test_tmp_config.py
my/core/tests/structure_data/gdpr_export.tar.gz
my/core/tests/structure_data/gdpr_export.zip
hpi-0.7.20250911.dist-info/METADATA
hpi-0.7.20250911.dist-info/WHEEL
hpi-0.7.20250911.dist-info/entry_points.txt
hpi-0.7.20250911.dist-info/licenses/LICENSE
hpi-0.7.20250911.dist-info/RECORD
