Metadata-Version: 2.4
Name: HPI
Version: 0.7.20250911
Summary: A Python interface to my life
Project-URL: Homepage, https://github.com/karlicoss/HPI
Author-email: "Dima Gerasimov (@karlicoss)" <karlicoss@gmail.com>
Maintainer-email: "Dima Gerasimov (@karlicoss)" <karlicoss@gmail.com>
License: MIT License
License-File: LICENSE
Requires-Python: >=3.10
Requires-Dist: click>=8.1
Requires-Dist: decorator
Requires-Dist: kompress>=0.2.20240918
Requires-Dist: more-itertools
Requires-Dist: platformdirs
Requires-Dist: pytz
Requires-Dist: typing-extensions
Provides-Extra: optional
Requires-Dist: cachew>=0.15.20231019; extra == 'optional'
Requires-Dist: colorlog; extra == 'optional'
Requires-Dist: enlighten; extra == 'optional'
Requires-Dist: mypy; extra == 'optional'
Requires-Dist: orjson; extra == 'optional'
Requires-Dist: pyfzf-iter; extra == 'optional'
